caption2text/__init__.py
caption2text/converter.py
caption2text-0.1.2.dist-info/LICENSE
caption2text-0.1.2.dist-info/METADATA
caption2text-0.1.2.dist-info/WHEEL
caption2text-0.1.2.dist-info/entry_points.txt
caption2text-0.1.2.dist-info/top_level.txt
caption2text-0.1.2.dist-info/RECORD
