Metadata-Version: 2.1
Name: caption2text
Version: 0.1.2
Summary: A lightweight Python module to convert VTT and SRT caption files into plain text transcripts.
Author-email: BlueBirdBack <avery@bluebirdback.com>
License: MIT License
Project-URL: Homepage, https://github.com/BlueBirdBack/caption2text
Keywords: captions,subtitles,vtt,srt,transcript
Classifier: License :: OSI Approved :: MIT License
Classifier: Programming Language :: Python
Classifier: Programming Language :: Python :: 3
Classifier: Programming Language :: Python :: 3.7
Classifier: Programming Language :: Python :: 3.8
Classifier: Programming Language :: Python :: 3.9
Classifier: Programming Language :: Python :: 3.10
Classifier: Programming Language :: Python :: 3.11
Classifier: Programming Language :: Python :: 3.12
Classifier: Intended Audience :: Developers
Classifier: Topic :: Multimedia :: Video
Classifier: Topic :: Text Processing
Requires-Python: >=3.7
License-File: LICENSE
